persistentidgenerator/__init__.py
persistentidgenerator/seqguidgen.py
daedal_persistentidgenerator-1.1.5.dist-info/LICENSE
daedal_persistentidgenerator-1.1.5.dist-info/METADATA
daedal_persistentidgenerator-1.1.5.dist-info/WHEEL
daedal_persistentidgenerator-1.1.5.dist-info/RECORD
