Metadata-Version: 2.3
Name: daedal-persistentidgenerator
Version: 1.1.5
Summary: This packages allows creating squential ids for financial entities. It's a fairly simple program that allocates 1 billion ids for each entity.
License: GNU General Public License v3.0
Keywords: guid,uniqueid,uuid,sequentialid
Author: Deb Mishra
Author-email: infra@daedal.org
Requires-Python: >=3.11,<4.0
Classifier: License :: Other/Proprietary License
Classifier: Programming Language :: Python :: 3
Classifier: Programming Language :: Python :: 3.11
Classifier: Programming Language :: Python :: 3.12
Classifier: Programming Language :: Python :: 3.13
Project-URL: Homepage, https://github.com/daedalinc/persistentidgenerator
Project-URL: Repository, https://github.com/daedalinc/persistentidgenerator
